matchtools/__init__.py
matchtools/_matchblock.py
matchtools/_utils.py
matchtools/dictionary.json
matchtools-0.1.2.dist-info/DESCRIPTION.rst
matchtools-0.1.2.dist-info/METADATA
matchtools-0.1.2.dist-info/RECORD
matchtools-0.1.2.dist-info/WHEEL
matchtools-0.1.2.dist-info/metadata.json
matchtools-0.1.2.dist-info/top_level.txt
