Metadata-Version: 2.0
Name: matchtools
Version: 0.1.2
Summary: A set of tools for data matching and manipulation
Home-page: https://github.com/matchtools/matchtools
Author: Anton Kupenko & Dawid Kaczmarski
Author-email: anton.kupenko@gmail.com, dawidkaczmarski@gmail.com
License: MIT
Keywords: match matching comparison data attributes alignment integration
Platform: UNKNOWN
Classifier: Development Status :: 5 - Production/Stable
Classifier: Intended Audience :: Developers
Classifier: Intended Audience :: Science/Research
Classifier: Topic :: Office/Business
Classifier: Topic :: Scientific/Engineering :: Information Analysis
Classifier: Topic :: Utilities
Classifier: Programming Language :: Python :: 3
Classifier: Programming Language :: Python :: 3.5
Classifier: Programming Language :: Python :: 3.6
Requires-Dist: datefinder
Requires-Dist: fuzzywuzzy
Requires-Dist: geopy
Requires-Dist: roman
